[
  {
    "title": "NFTicket",
    "description": "NFTicket is a platform to browse, create, buy, and sell event tickets as NFTs using blockchain. It integrates Metamask for secure crypto payments and offers digital memorabilia, modernizing and preserving the event experience. This innovative approach adds value by uniquely commemorating users' event experiences in a digital format.",
    "image": "src/project1.jpeg",
    "source": "https://github.com/tsubaric",
    "class": [ { "label": "Senior Design" } ],
    "skills": [
      { "label": "Node.js" },
      { "label": "React" },
      { "label": "Firebase" },
      { "label": "Blockchain" },
      { "label": "Metamask" },
      { "label": "NFTs" }
    ]
  },
  {
    "title": "Doctor & Patient Healthcare Portal",
    "description": "Developed a full-stack application facilitating patient appointments with doctors/nurses connected to MySQL. Implemented secure registration and login functionalities for admins, patients, and employees. Utilized Spring Boot dependencies including JPA Queries, Web, Security, and Thymeleaf for frontend. Established an admin CRUD board for user maintenance.",
    "image": "src/project2.jpeg",
    "source": "https://github.com/tsubaric",
    "class": [ { "label": "Software Engineering" } ],
    "skills": [
      { "label": "Java" },
      { "label": "Spring Boot" },
      { "label": "MySQL Server" },
      { "label": "JPA Queries" },
      { "label": "Thymeleaf HTML" }
    ]
  },
  {
    "title": "SeekerPro",
    "description": "A brief description of Project 3.",
    "image": "src/project3.jpeg",
    "source": "https://github.com/tsubaric",
    "class": [ { "label": "Internet of Things" } ],
    "skills": [
      { "label": "Demo" },
      { "label": "Docs" },
      { "label": "Video" }
    ]
  },
  {
    "title": "Pong Game",
    "description": "A brief description of Project 4.",
    "image": "src/project4.jpeg",
    "source": "https://github.com/tsubaric",
    "class": [ { "label": "Embedded Systems" } ],
    "skills": [
      { "label": "Demo" },
      { "label": "Docs" },
      { "label": "Video" }
    ]
  },
  {
    "title": "X Social Account Recommendations and Similarities",
    "description": "A brief description of Project 5.",
    "image": "src/project5.jpeg",
    "source": "https://github.com/tsubaric",
    "class": [ { "label": "Modern Databases" } ],
    "skills": [
      { "label": "Demo" },
      { "label": "Docs" },
      { "label": "Video" }
    ]
  },
  {
    "title": "Asteroids Game",
    "description": "Added features to Asteroids using topics including: OOP, dynamic memory allocation, SFML library, composition, inheritance, and polymorphism.",
    "image": "src/project6.jpeg",
    "source": "https://github.com/tsubaric",
    "class": [ { "label": "Computers in Engineering" } ],
    "skills": [
      { "label": "C++" },
      { "label": "Cmake" },
      { "label": "Computer Graphics" },
      { "label": "SFML" }
    ]
  },
  {
    "title": "Theory of Computation",
    "description": "A brief description of Project 7.",
    "image": "src/project7.jpeg",
    "source": "https://github.com/tsubaric",
    "class": [ { "label": "Theory of Computation" } ],
    "skills": [
      { "label": "Demo" },
      { "label": "Docs" },
      { "label": "Video" }
    ]
  },
  {
    "title": "Wordle",
    "description": "Remake of the NYT Classic, a word-guessing game where players have six attempts to guess a five-letter word. Each guess must be a valid five-letter word. The color of a tile will change to show how close the guess was. If the tile turns green, the letter is in the word and in the correct spot. If it turns yellow, the letter is in the word but not in the correct spot.",
    "image": "src/project8.jpeg",
    "source": "https://github.com/tsubaric",
    "class": [ { "label": "Software Design" } ],
    "skills": [
      { "label": "Demo" },
      { "label": "Docs" },
      { "label": "Video" }
    ]
  }
]